app/__init__.py
app/db.py
app/utils.py
wine_webscrapper-0.0.9.dist-info/METADATA
wine_webscrapper-0.0.9.dist-info/WHEEL
wine_webscrapper-0.0.9.dist-info/entry_points.txt
wine_webscrapper-0.0.9.dist-info/top_level.txt
wine_webscrapper-0.0.9.dist-info/RECORD
