Metadata-Version: 2.2
Name: wine_webscrapper
Version: 0.0.9
Summary: A web-scrapper that scraps wines from web.
Author-email: Soham Jobanputra <sohamjobanputra7@gmail.com>
Project-URL: Repository, https://github.com/Soham7777777/Imbiber.git
Requires-Python: >=3.12
Requires-Dist: python-dotenv==1.0.1
Requires-Dist: pydantic==2.9.2
Requires-Dist: mypy==1.13.0
Requires-Dist: SQLAlchemy==2.0.36
Requires-Dist: email_validator==2.2.0
Requires-Dist: selenium==4.27.1
Requires-Dist: click==8.1.8
